eratos_xarray/__init__.py
eratos_xarray/backend/eratos_.py
eratos_xarray-0.2.0.dist-info/LICENSE
eratos_xarray-0.2.0.dist-info/METADATA
eratos_xarray-0.2.0.dist-info/WHEEL
eratos_xarray-0.2.0.dist-info/entry_points.txt
eratos_xarray-0.2.0.dist-info/RECORD
