Metadata-Version: 2.3
Name: eratos-xarray
Version: 0.2.0
Summary: Xarray backend for Eratos SDK
License: MIT
Author: Chris Sharman
Author-email: chris.sharman@csiro.au
Requires-Python: >=3.8,<4.0
Classifier: License :: OSI Approved :: MIT License
Classifier: Programming Language :: Python :: 3
Classifier: Programming Language :: Python :: 3.8
Classifier: Programming Language :: Python :: 3.9
Classifier: Programming Language :: Python :: 3.10
Classifier: Programming Language :: Python :: 3.11
Classifier: Programming Language :: Python :: 3.12
Classifier: Programming Language :: Python :: 3.13
Requires-Dist: eratos-sdk (>=0.18.0,<1.0.0)
Requires-Dist: numpy (>=1.20.0,<2.0.0)
Requires-Dist: xarray (>=2023.1.0,<2024.0.0)
Project-URL: Homepage, https://bitbucket.csiro.au/projects/SC/repos/eratos-xarray/browse
Project-URL: Repository, https://bitbucket.csiro.au/projects/SC/repos/eratos-xarray/browse
